text_eval/__init__.py
text_eval/constants.py
text_eval/multiset_distance.py
TextGenerationEvaluationMetrics-0.0.1.dist-info/LICENSE
TextGenerationEvaluationMetrics-0.0.1.dist-info/METADATA
TextGenerationEvaluationMetrics-0.0.1.dist-info/WHEEL
TextGenerationEvaluationMetrics-0.0.1.dist-info/top_level.txt
TextGenerationEvaluationMetrics-0.0.1.dist-info/RECORD
